TracWikiAutoComplete-1.4.dist-info/DESCRIPTION.rst
TracWikiAutoComplete-1.4.dist-info/METADATA
TracWikiAutoComplete-1.4.dist-info/RECORD
TracWikiAutoComplete-1.4.dist-info/WHEEL
TracWikiAutoComplete-1.4.dist-info/entry_points.txt
TracWikiAutoComplete-1.4.dist-info/metadata.json
TracWikiAutoComplete-1.4.dist-info/top_level.txt
wikiautocomplete/__init__.py
wikiautocomplete/web_ui.py
wikiautocomplete/htdocs/css/jquery.textcomplete.css
wikiautocomplete/htdocs/js/jquery.textcomplete.min.js
wikiautocomplete/htdocs/js/wikiautocomplete.js
