Metadata-Version: 2.0
Name: TracWikiAutoComplete
Version: 1.4
Summary: Auto-completes wiki formatting
Home-page: https://trac-hacks.org/wiki/WikiAutoCompletePlugin
Author: Peter Suter
Author-email: peter@lucid.ch
License: BSD
Platform: UNKNOWN
Classifier: Framework :: Trac
